tempmail/__init__.py
tempmail/providers.py
tempmail/utils.py
tempmail_python-2.3.3.dist-info/LICENSE
tempmail_python-2.3.3.dist-info/METADATA
tempmail_python-2.3.3.dist-info/WHEEL
tempmail_python-2.3.3.dist-info/top_level.txt
tempmail_python-2.3.3.dist-info/RECORD
