Metadata-Version: 2.1
Name: tempmail-python
Version: 2.3.3
Summary: Python library for generating and managing temporary email addresses.
Home-page: https://github.com/cubicbyte/tempmail-python
Author: cubicbyte
Author-email: bmaruhnenko@gmail.com
License: MIT
Keywords: disposable-email temporary-email temp-email temp-mail email mail email-generator mail-generator
Classifier: Development Status :: 5 - Production/Stable
Classifier: Programming Language :: Python :: 3
Classifier: License :: OSI Approved :: MIT License
Requires-Python: >=3.7
License-File: LICENSE
Requires-Dist: requests>=2.19.0
